[{"key":"Atlantic, Southwest","region":"Argentina","value":800},{"key":"Atlantic, Northwest","region":"Germany","value":200},{"key":"Atlantic, Northeast","region":"Germany","value":500},{"key":"Atlantic, Eastern Central","region":"Greece","value":400},{"key":"Mediterranean and Black Sea","region":"Greece","value":300},{"key":"Indian Ocean, Eastern","region":"Indonesia","value":712},{"key":"Pacific, Northwest","region":"Korea, Republic of","value":800},{"key":"Atlantic, Western Central","region":"Mexico","value":3000},{"key":"Pacific, Southwest","region":"New Zealand","value":1300},{"key":"Atlantic, Northeast","region":"Norway","value":8800},{"key":"Indian Ocean, Western","region":"Pakistan","value":26100},{"key":"Pacific, Southeast","region":"Peru","value":800},{"key":"Atlantic, Northeast","region":"Portugal","value":300},{"key":"Atlantic, Northeast","region":"Spain","value":2800},{"key":"Mediterranean and Black Sea","region":"Turkey","value":5700},{"key":"Atlantic, Northwest","region":"Un. Sov. Soc. Rep.","value":2436},{"key":"Atlantic, Northwest","region":"United Kingdom","value":10},{"key":"Atlantic, Northwest","region":"United States of America","value":322},{"key":"Pacific, Northeast","region":"United States of America","value":569},{"key":"Atlantic, Western Central","region":"Venezuela, Boliv Rep of","value":1900},{"key":"Mediterranean and Black Sea","region":"Yugoslavia SFR","value":200}]