[{"key":"Atlantic, Southwest","region":"Argentina","value":2700},{"key":"Atlantic, Northeast","region":"Germany","value":100},{"key":"Mediterranean and Black Sea","region":"Greece","value":1000},{"key":"Atlantic, Northwest","region":"Iceland","value":200},{"key":"Indian Ocean, Eastern","region":"Indonesia","value":337},{"key":"Pacific, Northwest","region":"Korea, Republic of","value":8700},{"key":"Pacific, Southwest","region":"New Zealand","value":600},{"key":"Atlantic, Northeast","region":"Norway","value":600},{"key":"Indian Ocean, Western","region":"Pakistan","value":6300},{"key":"Atlantic, Northeast","region":"Portugal","value":1900},{"key":"Atlantic, Northeast","region":"Spain","value":6800},{"key":"Atlantic, Northwest","region":"United States of America","value":298},{"key":"Pacific, Northeast","region":"United States of America","value":1107},{"key":"Atlantic, Western Central","region":"Venezuela, Boliv Rep of","value":1100},{"key":"Mediterranean and Black Sea","region":"Yugoslavia SFR","value":100}]